{"efExports":[{"ValueRef":{"Ident":"charCodeAt"}},{"ValueRef":{"Ident":"charAt"}},{"ValueRef":{"Ident":"char"}}],"efImports":[{"eiImportedAs":null,"eiModule":["Prim"],"eiImportType":{"Implicit":[]}}],"efVersion":"0.8.0.0","efDeclarations":[{"EDValue":{"edValueType":{"tag":"TypeApp","contents":[{"tag":"TypeApp","contents":[{"tag":"TypeConstructor","contents":[["Prim"],"Function"]},{"tag":"TypeConstructor","contents":[["Prim"],"Int"]}]},{"tag":"TypeApp","contents":[{"tag":"TypeApp","contents":[{"tag":"TypeConstructor","contents":[["Prim"],"Function"]},{"tag":"TypeConstructor","contents":[["Prim"],"String"]}]},{"tag":"TypeConstructor","contents":[["Prim"],"Int"]}]}]},"edValueName":{"Ident":"charCodeAt"}}},{"EDValue":{"edValueType":{"tag":"TypeApp","contents":[{"tag":"TypeApp","contents":[{"tag":"TypeConstructor","contents":[["Prim"],"Function"]},{"tag":"TypeConstructor","contents":[["Prim"],"Int"]}]},{"tag":"TypeApp","contents":[{"tag":"TypeApp","contents":[{"tag":"TypeConstructor","contents":[["Prim"],"Function"]},{"tag":"TypeConstructor","contents":[["Prim"],"String"]}]},{"tag":"TypeConstructor","contents":[["Prim"],"Char"]}]}]},"edValueName":{"Ident":"charAt"}}},{"EDValue":{"edValueType":{"tag":"TypeApp","contents":[{"tag":"TypeApp","contents":[{"tag":"TypeConstructor","contents":[["Prim"],"Function"]},{"tag":"TypeConstructor","contents":[["Prim"],"String"]}]},{"tag":"TypeConstructor","contents":[["Prim"],"Char"]}]},"edValueName":{"Ident":"char"}}}],"efFixities":[],"efModuleName":["Data","String","Unsafe"]}