{"efExports":[{"TypeRef":["Wrap",["Wrap"]]},{"ValueRef":{"Ident":"unwrap"}},{"TypeInstanceRef":{"Ident":"wrapBifunctor"}},{"TypeInstanceRef":{"Ident":"wrapFunctor"}},{"TypeInstanceRef":{"Ident":"wrapBiapply"}},{"TypeInstanceRef":{"Ident":"wrapBiapplicative"}}],"efImports":[{"eiImportedAs":null,"eiModule":["Prim"],"eiImportType":{"Implicit":[]}},{"eiImportedAs":null,"eiModule":["Prelude"],"eiImportType":{"Implicit":[]}},{"eiImportedAs":null,"eiModule":["Control","Biapplicative"],"eiImportType":{"Implicit":[]}},{"eiImportedAs":null,"eiModule":["Control","Biapply"],"eiImportType":{"Implicit":[]}},{"eiImportedAs":null,"eiModule":["Data","Bifunctor"],"eiImportType":{"Implicit":[]}}],"efVersion":"0.8.0.0","efDeclarations":[{"EDType":{"edTypeName":"Wrap","edTypeKind":{"tag":"FunKind","contents":[{"tag":"FunKind","contents":[{"tag":"Star","contents":[]},{"tag":"FunKind","contents":[{"tag":"Star","contents":[]},{"tag":"Star","contents":[]}]}]},{"tag":"FunKind","contents":[{"tag":"Star","contents":[]},{"tag":"FunKind","contents":[{"tag":"Star","contents":[]},{"tag":"Star","contents":[]}]}]}]},"edTypeDeclarationKind":{"DataType":[[["p",{"tag":"FunKind","contents":[{"tag":"Star","contents":[]},{"tag":"FunKind","contents":[{"tag":"Star","contents":[]},{"tag":"Star","contents":[]}]}]}],["a",{"tag":"Star","contents":[]}],["b",{"tag":"Star","contents":[]}]],[["Wrap",[{"tag":"TypeApp","contents":[{"tag":"TypeApp","contents":[{"tag":"TypeVar","contents":"p"},{"tag":"TypeVar","contents":"a"}]},{"tag":"TypeVar","contents":"b"}]}]]]]}}},{"EDDataConstructor":{"edDataCtorName":"Wrap","edDataCtorFields":[{"Ident":"value0"}],"edDataCtorType":{"tag":"ForAll","contents":["b",{"tag":"ForAll","contents":["a",{"tag":"ForAll","contents":["p",{"tag":"TypeApp","contents":[{"tag":"TypeApp","contents":[{"tag":"TypeConstructor","contents":[["Prim"],"Function"]},{"tag":"TypeApp","contents":[{"tag":"TypeApp","contents":[{"tag":"TypeVar","contents":"p"},{"tag":"TypeVar","contents":"a"}]},{"tag":"TypeVar","contents":"b"}]}]},{"tag":"TypeApp","contents":[{"tag":"TypeApp","contents":[{"tag":"TypeApp","contents":[{"tag":"TypeConstructor","contents":[["Data","Bifunctor","Wrap"],"Wrap"]},{"tag":"TypeVar","contents":"p"}]},{"tag":"TypeVar","contents":"a"}]},{"tag":"TypeVar","contents":"b"}]}]},null]},null]},null]},"edDataCtorTypeCtor":"Wrap","edDataCtorOrigin":"data"}},{"EDValue":{"edValueType":{"tag":"ForAll","contents":["b",{"tag":"ForAll","contents":["a",{"tag":"ForAll","contents":["p",{"tag":"TypeApp","contents":[{"tag":"TypeApp","contents":[{"tag":"TypeConstructor","contents":[["Prim"],"Function"]},{"tag":"TypeApp","contents":[{"tag":"TypeApp","contents":[{"tag":"TypeApp","contents":[{"tag":"TypeConstructor","contents":[["Data","Bifunctor","Wrap"],"Wrap"]},{"tag":"TypeVar","contents":"p"}]},{"tag":"TypeVar","contents":"a"}]},{"tag":"TypeVar","contents":"b"}]}]},{"tag":"TypeApp","contents":[{"tag":"TypeApp","contents":[{"tag":"TypeVar","contents":"p"},{"tag":"TypeVar","contents":"a"}]},{"tag":"TypeVar","contents":"b"}]}]},28]},29]},30]},"edValueName":{"Ident":"unwrap"}}},{"EDInstance":{"edInstanceTypes":[{"tag":"TypeApp","contents":[{"tag":"TypeConstructor","contents":[["Data","Bifunctor","Wrap"],"Wrap"]},{"tag":"TypeVar","contents":"p"}]}],"edInstanceConstraints":[[[["Data","Bifunctor"],"Bifunctor"],[{"tag":"TypeVar","contents":"p"}]]],"edInstanceName":{"Ident":"wrapBifunctor"},"edInstanceClassName":[["Data","Bifunctor"],"Bifunctor"]}},{"EDInstance":{"edInstanceTypes":[{"tag":"TypeApp","contents":[{"tag":"TypeApp","contents":[{"tag":"TypeConstructor","contents":[["Data","Bifunctor","Wrap"],"Wrap"]},{"tag":"TypeVar","contents":"p"}]},{"tag":"TypeVar","contents":"a"}]}],"edInstanceConstraints":[[[["Data","Bifunctor"],"Bifunctor"],[{"tag":"TypeVar","contents":"p"}]]],"edInstanceName":{"Ident":"wrapFunctor"},"edInstanceClassName":[["Prelude"],"Functor"]}},{"EDInstance":{"edInstanceTypes":[{"tag":"TypeApp","contents":[{"tag":"TypeConstructor","contents":[["Data","Bifunctor","Wrap"],"Wrap"]},{"tag":"TypeVar","contents":"p"}]}],"edInstanceConstraints":[[[["Control","Biapply"],"Biapply"],[{"tag":"TypeVar","contents":"p"}]]],"edInstanceName":{"Ident":"wrapBiapply"},"edInstanceClassName":[["Control","Biapply"],"Biapply"]}},{"EDInstance":{"edInstanceTypes":[{"tag":"TypeApp","contents":[{"tag":"TypeConstructor","contents":[["Data","Bifunctor","Wrap"],"Wrap"]},{"tag":"TypeVar","contents":"p"}]}],"edInstanceConstraints":[[[["Control","Biapplicative"],"Biapplicative"],[{"tag":"TypeVar","contents":"p"}]]],"edInstanceName":{"Ident":"wrapBiapplicative"},"edInstanceClassName":[["Control","Biapplicative"],"Biapplicative"]}}],"efFixities":[],"efModuleName":["Data","Bifunctor","Wrap"]}