{"efExports":[{"ValueRef":{"Ident":"item"}},{"ValueRef":{"Ident":"length"}}],"efImports":[{"eiImportedAs":null,"eiModule":["Prim"],"eiImportType":{"Implicit":[]}},{"eiImportedAs":null,"eiModule":["Prelude"],"eiImportType":{"Implicit":[]}},{"eiImportedAs":null,"eiModule":["Control","Monad","Eff"],"eiImportType":{"Explicit":[{"PositionedDeclarationRef":[{"start":[5,27],"name":"/Users/paf31/Documents/Code/purescript/trypurescript/bower_components/purescript-dom/src/DOM/Node/NodeList.purs","end":[5,32]},[],{"TypeRef":["Eff",[]]}]}]}},{"eiImportedAs":null,"eiModule":["Data","Nullable"],"eiImportType":{"Explicit":[{"PositionedDeclarationRef":[{"start":[7,23],"name":"/Users/paf31/Documents/Code/purescript/trypurescript/bower_components/purescript-dom/src/DOM/Node/NodeList.purs","end":[7,33]},[],{"TypeRef":["Nullable",[]]}]}]}},{"eiImportedAs":null,"eiModule":["DOM"],"eiImportType":{"Implicit":[]}},{"eiImportedAs":null,"eiModule":["DOM","Node","Types"],"eiImportType":{"Implicit":[]}}],"efVersion":"0.8.0.0","efDeclarations":[{"EDValue":{"edValueType":{"tag":"ForAll","contents":["eff",{"tag":"TypeApp","contents":[{"tag":"TypeApp","contents":[{"tag":"TypeConstructor","contents":[["Prim"],"Function"]},{"tag":"TypeConstructor","contents":[["Prim"],"Int"]}]},{"tag":"TypeApp","contents":[{"tag":"TypeApp","contents":[{"tag":"TypeConstructor","contents":[["Prim"],"Function"]},{"tag":"TypeConstructor","contents":[["DOM","Node","Types"],"NodeList"]}]},{"tag":"TypeApp","contents":[{"tag":"TypeApp","contents":[{"tag":"TypeConstructor","contents":[["Control","Monad","Eff"],"Eff"]},{"tag":"RCons","contents":["dom",{"tag":"TypeConstructor","contents":[["DOM"],"DOM"]},{"tag":"TypeVar","contents":"eff"}]}]},{"tag":"TypeApp","contents":[{"tag":"TypeConstructor","contents":[["Data","Nullable"],"Nullable"]},{"tag":"TypeConstructor","contents":[["DOM","Node","Types"],"Node"]}]}]}]}]},null]},"edValueName":{"Ident":"item"}}},{"EDValue":{"edValueType":{"tag":"ForAll","contents":["eff",{"tag":"TypeApp","contents":[{"tag":"TypeApp","contents":[{"tag":"TypeConstructor","contents":[["Prim"],"Function"]},{"tag":"TypeConstructor","contents":[["DOM","Node","Types"],"NodeList"]}]},{"tag":"TypeApp","contents":[{"tag":"TypeApp","contents":[{"tag":"TypeConstructor","contents":[["Control","Monad","Eff"],"Eff"]},{"tag":"RCons","contents":["dom",{"tag":"TypeConstructor","contents":[["DOM"],"DOM"]},{"tag":"TypeVar","contents":"eff"}]}]},{"tag":"TypeConstructor","contents":[["Prim"],"Int"]}]}]},null]},"edValueName":{"Ident":"length"}}}],"efFixities":[],"efModuleName":["DOM","Node","NodeList"]}