{"efExports":[{"ValueRef":{"Ident":"amber"}},{"ValueRef":{"Ident":"blue"}},{"ValueRef":{"Ident":"blueGrey"}},{"ValueRef":{"Ident":"brown"}},{"ValueRef":{"Ident":"cyan"}},{"ValueRef":{"Ident":"deepOrange"}},{"ValueRef":{"Ident":"deepPurple"}},{"ValueRef":{"Ident":"green"}},{"ValueRef":{"Ident":"grey"}},{"ValueRef":{"Ident":"indigo"}},{"ValueRef":{"Ident":"lightBlue"}},{"ValueRef":{"Ident":"lightGreen"}},{"ValueRef":{"Ident":"lime"}},{"ValueRef":{"Ident":"orange"}},{"ValueRef":{"Ident":"pink"}},{"ValueRef":{"Ident":"purple"}},{"ValueRef":{"Ident":"red"}},{"ValueRef":{"Ident":"teal"}},{"ValueRef":{"Ident":"yellow"}}],"efImports":[{"eiImportedAs":null,"eiModule":["Prim"],"eiImportType":{"Implicit":[]}},{"eiImportedAs":null,"eiModule":["Color"],"eiImportType":{"Explicit":[{"PositionedDeclarationRef":[{"start":[5,15],"name":"/Users/phil/Documents/Code/purescript/trypurescript/staging/pux/bower_components/purescript-colors/src/Color/Scheme/MaterialDesign.purs","end":[5,22]},[],{"TypeRef":["Color",[]]}]},{"PositionedDeclarationRef":[{"start":[5,24],"name":"/Users/phil/Documents/Code/purescript/trypurescript/staging/pux/bower_components/purescript-colors/src/Color/Scheme/MaterialDesign.purs","end":[5,27]},[],{"ValueRef":{"Ident":"rgb"}}]}]}}],"efTypeFixities":[],"efVersion":"0.9.1","efDeclarations":[{"EDValue":{"edValueType":{"tag":"TypeConstructor","contents":[["Color"],"Color"]},"edValueName":{"Ident":"amber"}}},{"EDValue":{"edValueType":{"tag":"TypeConstructor","contents":[["Color"],"Color"]},"edValueName":{"Ident":"blue"}}},{"EDValue":{"edValueType":{"tag":"TypeConstructor","contents":[["Color"],"Color"]},"edValueName":{"Ident":"blueGrey"}}},{"EDValue":{"edValueType":{"tag":"TypeConstructor","contents":[["Color"],"Color"]},"edValueName":{"Ident":"brown"}}},{"EDValue":{"edValueType":{"tag":"TypeConstructor","contents":[["Color"],"Color"]},"edValueName":{"Ident":"cyan"}}},{"EDValue":{"edValueType":{"tag":"TypeConstructor","contents":[["Color"],"Color"]},"edValueName":{"Ident":"deepOrange"}}},{"EDValue":{"edValueType":{"tag":"TypeConstructor","contents":[["Color"],"Color"]},"edValueName":{"Ident":"deepPurple"}}},{"EDValue":{"edValueType":{"tag":"TypeConstructor","contents":[["Color"],"Color"]},"edValueName":{"Ident":"green"}}},{"EDValue":{"edValueType":{"tag":"TypeConstructor","contents":[["Color"],"Color"]},"edValueName":{"Ident":"grey"}}},{"EDValue":{"edValueType":{"tag":"TypeConstructor","contents":[["Color"],"Color"]},"edValueName":{"Ident":"indigo"}}},{"EDValue":{"edValueType":{"tag":"TypeConstructor","contents":[["Color"],"Color"]},"edValueName":{"Ident":"lightBlue"}}},{"EDValue":{"edValueType":{"tag":"TypeConstructor","contents":[["Color"],"Color"]},"edValueName":{"Ident":"lightGreen"}}},{"EDValue":{"edValueType":{"tag":"TypeConstructor","contents":[["Color"],"Color"]},"edValueName":{"Ident":"lime"}}},{"EDValue":{"edValueType":{"tag":"TypeConstructor","contents":[["Color"],"Color"]},"edValueName":{"Ident":"orange"}}},{"EDValue":{"edValueType":{"tag":"TypeConstructor","contents":[["Color"],"Color"]},"edValueName":{"Ident":"pink"}}},{"EDValue":{"edValueType":{"tag":"TypeConstructor","contents":[["Color"],"Color"]},"edValueName":{"Ident":"purple"}}},{"EDValue":{"edValueType":{"tag":"TypeConstructor","contents":[["Color"],"Color"]},"edValueName":{"Ident":"red"}}},{"EDValue":{"edValueType":{"tag":"TypeConstructor","contents":[["Color"],"Color"]},"edValueName":{"Ident":"teal"}}},{"EDValue":{"edValueType":{"tag":"TypeConstructor","contents":[["Color"],"Color"]},"edValueName":{"Ident":"yellow"}}}],"efFixities":[],"efModuleName":["Color","Scheme","MaterialDesign"]}